pyttp/__init__.py
pyttp/py.typed
pyttp/enums/__init__.py
pyttp/errors/__init__.py
pyttp/errors/http_error.py
pyttp-0.1.2.dist-info/METADATA
pyttp-0.1.2.dist-info/WHEEL
pyttp-0.1.2.dist-info/RECORD
