Metadata-Version: 2.3
Name: pyttp
Version: 0.1.2
Summary: Http utils for python REST APIs
Requires-Python: >=3.10
